rasamodelandtrain/__init__.py
rasamodelandtrain/rasa_id_interpreter.py
rasamodelandtrain-0.0.10.dist-info/LICENCE.txt
rasamodelandtrain-0.0.10.dist-info/METADATA
rasamodelandtrain-0.0.10.dist-info/WHEEL
rasamodelandtrain-0.0.10.dist-info/top_level.txt
rasamodelandtrain-0.0.10.dist-info/RECORD
